{"cameraMode":{"drawMode":0,"name":"Shaded","section":"Shading Mode"},"sceneLighting":true,"audioPlay":false,"sceneViewState":{"showFog":true,"showMaterialUpdate":false,"showSkybox":true,"showFlares":true,"showImageEffects":true,"showParticleSystems":true},"in2DMode":false,"pivot":{"x":1.2266871929168702,"y":-2.900583505630493,"z":7.069464206695557},"rotation":{"x":-0.1980755627155304,"y":-0.12284181267023087,"z":0.02503008209168911,"w":-0.972144365310669},"size":6.035979747772217,"orthographic":false}